electronome/Perc_Can_hi.wav
electronome/Perc_Can_lo.wav
electronome/__init__.py
electronome/config.py
electronome/electronome.py
electronome/mainwin.py
electronome/metronomethread.py
electronome-0.0.2.dist-info/licenses/LICENSE
electronome-0.0.2.dist-info/METADATA
electronome-0.0.2.dist-info/WHEEL
electronome-0.0.2.dist-info/entry_points.txt
electronome-0.0.2.dist-info/top_level.txt
electronome-0.0.2.dist-info/RECORD
