Metadata-Version: 2.4
Name: electronome
Version: 0.0.2
Summary: Configurable Qt metronome
Author-email: Matthew Baker <matt@mattbaker.ch>
License: 
Project-URL: repository, https://github.com/mbakereth/electronome
Keywords: feed,reader,tutorial
Classifier: License :: OSI Approved :: Apache Software License
Classifier: Programming Language :: Python
Classifier: Programming Language :: Python :: 3
Requires-Python: >=3.10
License-File: LICENSE
Requires-Dist: python-dotenv
Provides-Extra: build
Requires-Dist: build; extra == "build"
Requires-Dist: twine; extra == "build"
Dynamic: license-file
